[
  {
    "date": "26/02/2016",
    "type": {
      "eventType": "Pagamento de Juros",
      "id": 1,
      "isFinal": "NÃO"
    },
    "isIncorporaJuros": false,
    "isRemove": false
  },
  {
    "date": "26/02/2013",
    "type": {
      "eventType": "Vencimento (Resgate)",
      "id": 1,
      "isFinal": "NÃO"
    },
    "isIncorporaJuros": false,
    "isRemove": false
  },
  {
    "date": "26/02/2011",
    "type": {
      "eventType": "Pagamento de Amortização",
      "id": 1,
      "isFinal": "NÃO"
    },
    "isIncorporaJuros": false,
    "isRemove": false
  },
  {
    "date": "26/02/1980",
    "type": {
      "eventType": "Pagamento de Juros",
      "id": 1,
      "isFinal": "NÃO"
    },
    "isIncorporaJuros": true
  },
  {
    "date": "26/02/1980",
    "type": {
      "eventType": "Pagamento de Juros",
      "id": 1,
      "isFinal": "NÃO"
    },
    "isIncorporaJuros": true
  },
  {
    "date": "26/02/1980",
    "type": {
      "eventType": "Pagamento de Juros",
      "id": 1,
      "isFinal": "NÃO"
    },
    "isIncorporaJuros": true
  },
  {
    "date": "26/02/1980",
    "type": {
      "eventType": "Pagamento de Juros",
      "id": 1,
      "isFinal": "NÃO"
    },
    "isIncorporaJuros": true
  },
  {
    "date": "26/02/1980",
    "type": {
      "eventType": "Pagamento de Juros",
      "id": 1,
      "isFinal": "NÃO"
    },
    "isIncorporaJuros": true
  },
  {
    "date": "26/02/2015",
    "type": {
      "eventType": "Pagamento de Amortização",
      "id": 3,
      "isFinal": "NÃO"
    },
    "isIncorporaJuros": false
  },
  {
    "date": "26/01/1999",
    "type": {
      "eventType": "Pagamento de Amortização",
      "id": 3,
      "isFinal": "NÃO"
    },
    "isIncorporaJuros": true
  },
  {
    "date": "26/01/2000",
    "type": {
      "eventType": "Pagamento de Juros",
      "id": 1,
      "isFinal": "NÃO"
    },
    "isIncorporaJuros": false
  },
  {
    "date": "26/10/2016",
    "type": {
      "eventType": "Pagamento de Amortização",
      "id": 3,
      "isFinal": "NÃO"
    },
    "isIncorporaJuros": false
  },
  {
    "date": "26/11/2016",
    "type": {
      "eventType": "Pagamento de Juros",
      "id": 1,
      "isFinal": "NÃO"
    },
    "isIncorporaJuros": true
  },
  {
    "date": "26/01/1999",
    "type": {
      "eventType": "Pagamento de Amortização",
      "id": 3,
      "isFinal": "NÃO"
    },
    "isIncorporaJuros": false
  },
  {
    "isIncorporaJuros": true,
    "date": "26/02/1981",
    "type": {
      "eventType": "Pagamento de Amortização",
      "id": 3,
      "isFinal": "NÃO"
    }
  },
  {
    "date": "26/02/2012",
    "type": {
      "eventType": "Pagamento de Amortização",
      "id": 3,
      "isFinal": "NÃO"
    },
    "isIncorporaJuros": true
  },
  {
    "date": "12/01/2015",
    "type": {
      "eventType": "Pagamento de Amortização",
      "id": 3,
      "isFinal": "NÃO"
    },
    "isIncorporaJuros": true
  }
]
